{"cameraMode":{"drawMode":0,"name":"Shaded","section":"Shading Mode"},"sceneLighting":true,"audioPlay":false,"sceneViewState":{"showFog":true,"showMaterialUpdate":false,"showSkybox":true,"showFlares":true,"showImageEffects":true,"showParticleSystems":true},"in2DMode":false,"pivot":{"x":0.43425580859184267,"y":1.6685346364974976,"z":-7.435025691986084},"rotation":{"x":-0.22628846764564515,"y":0.36116349697113039,"z":-0.09080185741186142,"w":-0.9000608325004578},"size":5.563383638218511e-7,"orthographic":false}